gscal/__init__.py
gscal/__main__.py
gscal/gscal.py
gscal/data/help.txt
gscal-0.3.1.dist-info/LICENSE
gscal-0.3.1.dist-info/METADATA
gscal-0.3.1.dist-info/WHEEL
gscal-0.3.1.dist-info/entry_points.txt
gscal-0.3.1.dist-info/top_level.txt
gscal-0.3.1.dist-info/RECORD
