Metadata-Version: 2.1
Name: gscal
Version: 0.3.1
Summary: GTK Simple Calendar
Home-page: https://github.com/Akmadan23/gscal
Author: Azad Ahmadi
Author-email: azadahmadi@mailo.com
License: GPL-3
Classifier: Programming Language :: Python :: 3
Classifier: License :: OSI Approved :: GNU General Public License (GPL)
Classifier: Operating System :: OS Independent
Requires-Python: >=3.6
License-File: LICENSE
Requires-Dist: PyGObject
Requires-Dist: toml
